Workbook
Name Insumos: TablaInsumos[Nombre]
Name Platillo: TablaPlatillos[Nombre de Platillo]
Name Recepción: Insumos!$L$6:$L$8
Name Unidades: Tabla2[Unidades]

Sheet Inicio

Sheet Insumos
B3: 🥑 LISTADO DE INSUMOS E INGREDIENTES
L5: Recepción | M5: Unidades
L6: Sucursal | M6: Paquete
B7: Porcentaje Estimado de Costo Logístico: | D7: El porcentaje de costo logístico es el incremento en el costo de los insumos proveniente de traslados y/o almacenamiento de los insumos comprados en caso de contar con un CEDIS o Centro de Distribución. | L7: CEDIS | M7: Kilo
C8: ¿Cómo recibes el insumo? | G8: % Estimado de Merma | I8: Afectación según recepción de compra | L8: Almacén | M8: Litro
B9: Nombre | C9: Recepción de Compra | D9: Costo de Compra | E9: Cantidad | F9: Unidad de Compra | G9: % Merma | H9: Costo Unitario | I9: Costo Logístico | J9: Costo Unitario Total | M9: Onza
B10: Harina | C10: Sucursal | D10: 2250 | E10: 500 | F10: Gramo | G10: 0.02 | H10: =TablaInsumos[[#This Row],[Costo de Compra]]/TablaInsumos[[#This Row],[Cantidad]] -> 4.5 | I10: =IF(TablaInsumos[[#This Row],[Unidad de Compra]]="","",IF(TablaInsumos[[#This Row],[Recepción de Compra]]="CEDIS",$C$7,"")) | J10: =IF(TablaInsumos[[#This Row],[Costo Logístico]]="",TablaInsumos[[#This Row],[Costo Unitario]],TablaInsumos[[#This Row],[Costo Unitario]]*(1+TablaInsumos[[#This Row],[Costo Logístico]])) -> 4.5 | M10: Gramo
B11: Azúcar | C11: Sucursal | D11: 5100 | E11: 1000 | F11: Gramo | G11: 0.01 | H11: =TablaInsumos[[#This Row],[Costo de Compra]]/TablaInsumos[[#This Row],[Cantidad]] -> 5.1 | I11: =IF(TablaInsumos[[#This Row],[Unidad de Compra]]="","",IF(TablaInsumos[[#This Row],[Recepción de Compra]]="CEDIS",$C$7,"")) | J11: =IF(TablaInsumos[[#This Row],[Costo Logístico]]="",TablaInsumos[[#This Row],[Costo Unitario]],TablaInsumos[[#This Row],[Costo Unitario]]*(1+TablaInsumos[[#This Row],[Costo Logístico]])) -> 5.1 | M11: Libra
B12: Vitina (margarina) | C12: Sucursal | D12: 6500 | E12: 500 | F12: Gramo | G12: 0.02 | H12: =TablaInsumos[[#This Row],[Costo de Compra]]/TablaInsumos[[#This Row],[Cantidad]] -> 13 | I12: =IF(TablaInsumos[[#This Row],[Unidad de Compra]]="","",IF(TablaInsumos[[#This Row],[Recepción de Compra]]="CEDIS",$C$7,"")) | J12: =IF(TablaInsumos[[#This Row],[Costo Logístico]]="",TablaInsumos[[#This Row],[Costo Unitario]],TablaInsumos[[#This Row],[Costo Unitario]]*(1+TablaInsumos[[#This Row],[Costo Logístico]])) -> 13 | M12: Mililitro
B13: Azúcar glas | C13: Sucursal | D13: 4550 | E13: 500 | F13: Gramo | G13: 0.02 | H13: =TablaInsumos[[#This Row],[Costo de Compra]]/TablaInsumos[[#This Row],[Cantidad]] -> 9.1 | I13: =IF(TablaInsumos[[#This Row],[Unidad de Compra]]="","",IF(TablaInsumos[[#This Row],[Recepción de Compra]]="CEDIS",$C$7,"")) | J13: =IF(TablaInsumos[[#This Row],[Costo Logístico]]="",TablaInsumos[[#This Row],[Costo Unitario]],TablaInsumos[[#This Row],[Costo Unitario]]*(1+TablaInsumos[[#This Row],[Costo Logístico]])) -> 9.1 | M13: Rollo
B14: Huevos | C14: Sucursal | D14: 26700 | E14: 30 | F14: Unidad | G14: 0.05 | H14: =TablaInsumos[[#This Row],[Costo de Compra]]/TablaInsumos[[#This Row],[Cantidad]] -> 890 | I14: =IF(TablaInsumos[[#This Row],[Unidad de Compra]]="","",IF(TablaInsumos[[#This Row],[Recepción de Compra]]="CEDIS",$C$7,"")) | J14: =IF(TablaInsumos[[#This Row],[Costo Logístico]]="",TablaInsumos[[#This Row],[Costo Unitario]],TablaInsumos[[#This Row],[Costo Unitario]]*(1+TablaInsumos[[#This Row],[Costo Logístico]])) -> 890 | M14: Galón
B15: Sal (pizca) | C15: Sucursal | D15: 50 | E15: 1 | F15: Unidad | G15: 0.02 | H15: =TablaInsumos[[#This Row],[Costo de Compra]]/TablaInsumos[[#This Row],[Cantidad]] -> 50 | I15: =IF(TablaInsumos[[#This Row],[Unidad de Compra]]="","",IF(TablaInsumos[[#This Row],[Recepción de Compra]]="CEDIS",$C$7,"")) | J15: =IF(TablaInsumos[[#This Row],[Costo Logístico]]="",TablaInsumos[[#This Row],[Costo Unitario]],TablaInsumos[[#This Row],[Costo Unitario]]*(1+TablaInsumos[[#This Row],[Costo Logístico]])) -> 50 | M15: Metro
B16: Leche entera | C16: Sucursal | D16: 4490 | E16: 1000 | F16: Mililitro | G16: 0.01 | H16: =TablaInsumos[[#This Row],[Costo de Compra]]/TablaInsumos[[#This Row],[Cantidad]] -> 4.49 | I16: =IF(TablaInsumos[[#This Row],[Unidad de Compra]]="","",IF(TablaInsumos[[#This Row],[Recepción de Compra]]="CEDIS",$C$7,"")) | J16: =IF(TablaInsumos[[#This Row],[Costo Logístico]]="",TablaInsumos[[#This Row],[Costo Unitario]],TablaInsumos[[#This Row],[Costo Unitario]]*(1+TablaInsumos[[#This Row],[Costo Logístico]])) -> 4.49 | M16: Unidad
B17: Polvo para hornear | C17: Sucursal | D17: 7520 | E17: 80 | F17: Gramo | G17: 0.055 | H17: =TablaInsumos[[#This Row],[Costo de Compra]]/TablaInsumos[[#This Row],[Cantidad]] -> 94 | I17: =IF(TablaInsumos[[#This Row],[Unidad de Compra]]="","",IF(TablaInsumos[[#This Row],[Recepción de Compra]]="CEDIS",$C$7,"")) | J17: =IF(TablaInsumos[[#This Row],[Costo Logístico]]="",TablaInsumos[[#This Row],[Costo Unitario]],TablaInsumos[[#This Row],[Costo Unitario]]*(1+TablaInsumos[[#This Row],[Costo Logístico]])) -> 94
B18: Galletas Oreo | C18: Sucursal | D18: 13100 | E18: 10 | F18: Paquete | G18: 0.03 | H18: =TablaInsumos[[#This Row],[Costo de Compra]]/TablaInsumos[[#This Row],[Cantidad]] -> 1310 | I18: =IF(TablaInsumos[[#This Row],[Unidad de Compra]]="","",IF(TablaInsumos[[#This Row],[Recepción de Compra]]="CEDIS",$C$7,"")) | J18: =IF(TablaInsumos[[#This Row],[Costo Logístico]]="",TablaInsumos[[#This Row],[Costo Unitario]],TablaInsumos[[#This Row],[Costo Unitario]]*(1+TablaInsumos[[#This Row],[Costo Logístico]])) -> 1310
B19: Esencia de vainilla | C19: Sucursal | D19: 4800 | E19: 155 | F19: Mililitro | G19: 0 | H19: =TablaInsumos[[#This Row],[Costo de Compra]]/TablaInsumos[[#This Row],[Cantidad]] -> 30.967742 | I19: =IF(TablaInsumos[[#This Row],[Unidad de Compra]]="","",IF(TablaInsumos[[#This Row],[Recepción de Compra]]="CEDIS",$C$7,"")) | J19: =IF(TablaInsumos[[#This Row],[Costo Logístico]]="",TablaInsumos[[#This Row],[Costo Unitario]],TablaInsumos[[#This Row],[Costo Unitario]]*(1+TablaInsumos[[#This Row],[Costo Logístico]])) -> 30.967742
B20: Mantequilla | C20: Sucursal | D20: 15550 | E20: 250 | F20: Gramo | G20: 0 | H20: =TablaInsumos[[#This Row],[Costo de Compra]]/TablaInsumos[[#This Row],[Cantidad]] -> 62.2 | I20: =IF(TablaInsumos[[#This Row],[Unidad de Compra]]="","",IF(TablaInsumos[[#This Row],[Recepción de Compra]]="CEDIS",$C$7,"")) | J20: =IF(TablaInsumos[[#This Row],[Costo Logístico]]="",TablaInsumos[[#This Row],[Costo Unitario]],TablaInsumos[[#This Row],[Costo Unitario]]*(1+TablaInsumos[[#This Row],[Costo Logístico]])) -> 62.2
B21: Base de cartón torta | C21: Sucursal | D21: 1500 | E21: 1 | F21: Unidad | G21: 0 | H21: =TablaInsumos[[#This Row],[Costo de Compra]]/TablaInsumos[[#This Row],[Cantidad]] -> 1500 | I21: =IF(TablaInsumos[[#This Row],[Unidad de Compra]]="","",IF(TablaInsumos[[#This Row],[Recepción de Compra]]="CEDIS",$C$7,"")) | J21: =IF(TablaInsumos[[#This Row],[Costo Logístico]]="",TablaInsumos[[#This Row],[Costo Unitario]],TablaInsumos[[#This Row],[Costo Unitario]]*(1+TablaInsumos[[#This Row],[Costo Logístico]])) -> 1500
B22: Capacillo | C22: Sucursal | D22: 6000 | E22: 100 | F22: Unidad | G22: 0 | H22: =TablaInsumos[[#This Row],[Costo de Compra]]/TablaInsumos[[#This Row],[Cantidad]] -> 60 | I22: =IF(TablaInsumos[[#This Row],[Unidad de Compra]]="","",IF(TablaInsumos[[#This Row],[Recepción de Compra]]="CEDIS",$C$7,"")) | J22: =IF(TablaInsumos[[#This Row],[Costo Logístico]]="",TablaInsumos[[#This Row],[Costo Unitario]],TablaInsumos[[#This Row],[Costo Unitario]]*(1+TablaInsumos[[#This Row],[Costo Logístico]])) -> 60
B23: Caja x12 cupcakes | C23: Sucursal | D23: 5500 | E23: 1 | F23: Unidad | G23: 0 | H23: =TablaInsumos[[#This Row],[Costo de Compra]]/TablaInsumos[[#This Row],[Cantidad]] -> 5500 | I23: =IF(TablaInsumos[[#This Row],[Unidad de Compra]]="","",IF(TablaInsumos[[#This Row],[Recepción de Compra]]="CEDIS",$C$7,"")) | J23: =IF(TablaInsumos[[#This Row],[Costo Logístico]]="",TablaInsumos[[#This Row],[Costo Unitario]],TablaInsumos[[#This Row],[Costo Unitario]]*(1+TablaInsumos[[#This Row],[Costo Logístico]])) -> 5500
D24: =SUBTOTAL(109,TablaInsumos[Costo de Compra]) -> 103610 | G24: =SUBTOTAL(101,TablaInsumos[% Merma]) -> 0.016785714 | I24: =IFERROR(SUBTOTAL(101,TablaInsumos[Costo Logístico]),"") | J24: =J10+J11+J12+J13+J14+J15+J16+J17+J18+J19+J20+J21+J22+J23 -> 9533.3577
B26: Nota: el costo de cada producto se calcula con las cantidades por unidad de la hoja Postre (Insumo / Cantidad) y el costo unitario de esta hoja.
B27: Precios corregidos según los PDF "Costos y utilidad - Torta de vainilla" (28/09/2026) y "Costos y precio comercial - Cupcakes de vainilla" (29/09/2026).
B28: Fuentes de los PDF: Éxito (harina, azúcar, mantequilla, huevos, leche, polvo, azúcar pulverizada), Mercacentro (esencia), Dispropan Caribe (Vitina Hojaldre), Orquídea (capacillos), Los Cartujos (caja x12). Base de cartón y sal: estimados.
B29: Unidades estandarizadas a gramo / mililitro / unidad. El % de merma es informativo: las fórmulas de la plantilla no lo aplican (los PDF tampoco).

Sheet Postre
B3: 🌮 PRODUCCIÓN DE POSTRES Y TORTAS
B7: INFORMACIÓN GENERAL | F7: GASTOS DIRECTOS | I7: GASTOS INDIRECTOS | L7: Ingresos | M7: =C8 -> 75000
B8: Precio de venta (producto elegido) | C8: =IFERROR(INDEX(TablaPlatillos[Precio Platillo],MATCH(Explosión!$C$10,TablaPlatillos[Nombre de Platillo],0)),0) -> 75000 | D8: Según el producto elegido en Explosión | F8: Mano de Obra | G8: =IFERROR(INDEX(TablaPlatillos[Mano de Obra],MATCH(Explosión!$C$10,TablaPlatillos[Nombre de Platillo],0)),0)*$C$9 -> 15000 | I8: Sueldos Admin. | J8: =IFERROR(INDEX(TablaPlatillos[Sueldos Admin.],MATCH(Explosión!$C$10,TablaPlatillos[Nombre de Platillo],0)),0)*$C$9 -> 0 | L8: Insumos | M8: =Explosión!$G$28 -> 40837.016
B9: Unidades por lote | C9: =IF(ISNUMBER(SEARCH("CopCake",Explosión!$C$10)),30,1) -> 1 | D9: Automático: 30 si es cupcake, 1 si es torta | F9: Servicios (Agua, Luz, Gas) | G9: =IFERROR(INDEX(TablaPlatillos[Servicios],MATCH(Explosión!$C$10,TablaPlatillos[Nombre de Platillo],0)),0)*$C$9 -> 2500 | I9: Depreciación / desgaste | J9: =Explosión!$G$40*$C$9 -> 16662.984 | L9: Gastos Directos | M9: =SUM(G8:G10)/$C$9 -> 17500
B10: % Utilidad Deseada | C10: 0.3 | D10: Margen objetivo sobre venta | F10: Gastos Oper. / Domicilio | G10: =IFERROR(INDEX(TablaPlatillos[Oper. Domicilio],MATCH(Explosión!$C$10,TablaPlatillos[Nombre de Platillo],0)),0)*$C$9 -> 0 | I10: Otros Gastos | J10: =IFERROR(INDEX(TablaPlatillos[Otros Gastos],MATCH(Explosión!$C$10,TablaPlatillos[Nombre de Platillo],0)),0)*$C$9 -> 0 | L10: Gastos Indirectos | M10: =SUM(J8:J10)/$C$9 -> 16662.984
B12: Nombre de Platillo | C12: Precio Platillo | D12: Insumo 1 | E12: Unidad 1 | F12: Cantidad 1 | G12: Insumo 2 | H12: Unidad 2 | I12: Cantidad 2 | J12: Insumo 3 | K12: Unidad 3 | L12: Cantidad 3 | M12: Insumo 4 | N12: Unidad 4 | O12: Cantidad 4 | P12: Insumo 5 | Q12: Unidad 5 | R12: Cantidad 5 | S12: Insumo 6 | T12: Unidad 6 | U12: Cantidad 6 | V12: Insumo 7 | W12: Unidad 7 | X12: Cantidad 7 | Y12: Insumo 8 | Z12: Unidad 8 | AA12: Cantidad 8 | AB12: Insumo 9 | AC12: Unidad 9 | AD12: Cantidad 9 | AE12: Insumo 10 | AF12: Unidad 10 | AG12: Cantidad 10 | AH12: Insumo 11 | AI12: Unidad 11 | AJ12: Cantidad 11 | AK12: Insumo 12 | AL12: Unidad 12 | AM12: Cantidad 12 | AN12: Mano de Obra | AO12: Servicios | AP12: Oper. Domicilio | AQ12: Sueldos Admin. | AR12: Depreciación | AS12: Otros Gastos
A13: 1 | B13: Torta Vainilla - Vitina | C13: 75000 | D13: Harina | E13: =IFERROR(INDEX(TablaInsumos[Unidad de Compra],MATCH(TablaPlatillos[[#This Row],[Insumo 1]],TablaInsumos[Nombre],0)),"") -> Gramo | F13: 500 | G13: Azúcar | H13: =IFERROR(INDEX(TablaInsumos[Unidad de Compra],MATCH(TablaPlatillos[[#This Row],[Insumo 2]],TablaInsumos[Nombre],0)),"") -> Gramo | I13: 400 | J13: Vitina (margarina) | K13: =IFERROR(INDEX(TablaInsumos[Unidad de Compra],MATCH(TablaPlatillos[[#This Row],[Insumo 3]],TablaInsumos[Nombre],0)),"") -> Gramo | L13: 400 | M13: Huevos | N13: =IFERROR(INDEX(TablaInsumos[Unidad de Compra],MATCH(TablaPlatillos[[#This Row],[Insumo 4]],TablaInsumos[Nombre],0)),"") -> Unidad | O13: 8 | P13: Leche entera | Q13: =IFERROR(INDEX(TablaInsumos[Unidad de Compra],MATCH(TablaPlatillos[[#This Row],[Insumo 5]],TablaInsumos[Nombre],0)),"") -> Mililitro | R13: 250 | S13: Polvo para hornear | T13: =IFERROR(INDEX(TablaInsumos[Unidad de Compra],MATCH(TablaPlatillos[[#This Row],[Insumo 6]],TablaInsumos[Nombre],0)),"") -> Gramo | U13: 15 | V13: Esencia de vainilla | W13: =IFERROR(INDEX(TablaInsumos[Unidad de Compra],MATCH(TablaPlatillos[[#This Row],[Insumo 7]],TablaInsumos[Nombre],0)),"") -> Mililitro | X13: 15 | Y13: Sal (pizca) | Z13: =IFERROR(INDEX(TablaInsumos[Unidad de Compra],MATCH(TablaPlatillos[[#This Row],[Insumo 8]],TablaInsumos[Nombre],0)),"") -> Unidad | AA13: 1 | AB13: Base de cartón torta | AC13: =IFERROR(INDEX(TablaInsumos[Unidad de Compra],MATCH(TablaPlatillos[[#This Row],[Insumo 9]],TablaInsumos[Nombre],0)),"") -> Unidad | AD13: 1 | AF13: =IFERROR(INDEX(TablaInsumos[Unidad de Compra],MATCH(TablaPlatillos[[#This Row],[Insumo 10]],TablaInsumos[Nombre],0)),"") | AI13: =IFERROR(INDEX(TablaInsumos[Unidad de Compra],MATCH(TablaPlatillos[[#This Row],[Insumo 11]],TablaInsumos[Nombre],0)),"") | AL13: =IFERROR(INDEX(TablaInsumos[Unidad de Compra],MATCH(TablaPlatillos[[#This Row],[Insumo 12]],TablaInsumos[Nombre],0)),"") | AN13: 15000 | AO13: =2000+500 -> 2500 | AP13: 0 | AQ13: 0 | AR13: =$J$26 -> 31666.667 | AS13: 0
A14: 2 | B14: Torta Vainilla - Mantequilla | C14: 75000 | D14: Harina | E14: =IFERROR(INDEX(TablaInsumos[Unidad de Compra],MATCH(TablaPlatillos[[#This Row],[Insumo 1]],TablaInsumos[Nombre],0)),"") -> Gramo | F14: 500 | G14: Azúcar | H14: =IFERROR(INDEX(TablaInsumos[Unidad de Compra],MATCH(TablaPlatillos[[#This Row],[Insumo 2]],TablaInsumos[Nombre],0)),"") -> Gramo | I14: 400 | J14: Mantequilla | K14: =IFERROR(INDEX(TablaInsumos[Unidad de Compra],MATCH(TablaPlatillos[[#This Row],[Insumo 3]],TablaInsumos[Nombre],0)),"") -> Gramo | L14: 400 | M14: Huevos | N14: =IFERROR(INDEX(TablaInsumos[Unidad de Compra],MATCH(TablaPlatillos[[#This Row],[Insumo 4]],TablaInsumos[Nombre],0)),"") -> Unidad | O14: 8 | P14: Leche entera | Q14: =IFERROR(INDEX(TablaInsumos[Unidad de Compra],MATCH(TablaPlatillos[[#This Row],[Insumo 5]],TablaInsumos[Nombre],0)),"") -> Mililitro | R14: 250 | S14: Polvo para hornear | T14: =IFERROR(INDEX(TablaInsumos[Unidad de Compra],MATCH(TablaPlatillos[[#This Row],[Insumo 6]],TablaInsumos[Nombre],0)),"") -> Gramo | U14: 15 | V14: Esencia de vainilla | W14: =IFERROR(INDEX(TablaInsumos[Unidad de Compra],MATCH(TablaPlatillos[[#This Row],[Insumo 7]],TablaInsumos[Nombre],0)),"") -> Mililitro | X14: 15 | Y14: Sal (pizca) | Z14: =IFERROR(INDEX(TablaInsumos[Unidad de Compra],MATCH(TablaPlatillos[[#This Row],[Insumo 8]],TablaInsumos[Nombre],0)),"") -> Unidad | AA14: 1 | AB14: Base de cartón torta | AC14: =IFERROR(INDEX(TablaInsumos[Unidad de Compra],MATCH(TablaPlatillos[[#This Row],[Insumo 9]],TablaInsumos[Nombre],0)),"") -> Unidad | AD14: 1 | AF14: =IFERROR(INDEX(TablaInsumos[Unidad de Compra],MATCH(TablaPlatillos[[#This Row],[Insumo 10]],TablaInsumos[Nombre],0)),"") | AI14: =IFERROR(INDEX(TablaInsumos[Unidad de Compra],MATCH(TablaPlatillos[[#This Row],[Insumo 11]],TablaInsumos[Nombre],0)),"") | AL14: =IFERROR(INDEX(TablaInsumos[Unidad de Compra],MATCH(TablaPlatillos[[#This Row],[Insumo 12]],TablaInsumos[Nombre],0)),"") | AN14: 15000 | AO14: =2000+500 -> 2500 | AP14: 0 | AQ14: 0 | AR14: =$J$26 -> 31666.667 | AS14: 0
A15: 3 | B15: CopCake vainilla - Vitina | C15: 4500 | D15: Harina | E15: =IFERROR(INDEX(TablaInsumos[Unidad de Compra],MATCH(TablaPlatillos[[#This Row],[Insumo 1]],TablaInsumos[Nombre],0)),"") -> Gramo | F15: =500/30 -> 16.666667 | G15: Azúcar | H15: =IFERROR(INDEX(TablaInsumos[Unidad de Compra],MATCH(TablaPlatillos[[#This Row],[Insumo 2]],TablaInsumos[Nombre],0)),"") -> Gramo | I15: =400/30 -> 13.333333 | J15: Vitina (margarina) | K15: =IFERROR(INDEX(TablaInsumos[Unidad de Compra],MATCH(TablaPlatillos[[#This Row],[Insumo 3]],TablaInsumos[Nombre],0)),"") -> Gramo | L15: =400/30 -> 13.333333 | M15: Huevos | N15: =IFERROR(INDEX(TablaInsumos[Unidad de Compra],MATCH(TablaPlatillos[[#This Row],[Insumo 4]],TablaInsumos[Nombre],0)),"") -> Unidad | O15: =8/30 -> 0.26666667 | P15: Leche entera | Q15: =IFERROR(INDEX(TablaInsumos[Unidad de Compra],MATCH(TablaPlatillos[[#This Row],[Insumo 5]],TablaInsumos[Nombre],0)),"") -> Mililitro | R15: =250/30 -> 8.3333333 | S15: Polvo para hornear | T15: =IFERROR(INDEX(TablaInsumos[Unidad de Compra],MATCH(TablaPlatillos[[#This Row],[Insumo 6]],TablaInsumos[Nombre],0)),"") -> Gramo | U15: =15/30 -> 0.5 | V15: Esencia de vainilla | W15: =IFERROR(INDEX(TablaInsumos[Unidad de Compra],MATCH(TablaPlatillos[[#This Row],[Insumo 7]],TablaInsumos[Nombre],0)),"") -> Mililitro | X15: =15/30 -> 0.5 | Y15: Sal (pizca) | Z15: =IFERROR(INDEX(TablaInsumos[Unidad de Compra],MATCH(TablaPlatillos[[#This Row],[Insumo 8]],TablaInsumos[Nombre],0)),"") -> Unidad | AA15: =1/30 -> 0.033333333 | AB15: Capacillo | AC15: =IFERROR(INDEX(TablaInsumos[Unidad de Compra],MATCH(TablaPlatillos[[#This Row],[Insumo 9]],TablaInsumos[Nombre],0)),"") -> Unidad | AD15: 1 | AE15: Caja x12 cupcakes | AF15: =IFERROR(INDEX(TablaInsumos[Unidad de Compra],MATCH(TablaPlatillos[[#This Row],[Insumo 10]],TablaInsumos[Nombre],0)),"") -> Unidad | AG15: =3/30 -> 0.1 | AI15: =IFERROR(INDEX(TablaInsumos[Unidad de Compra],MATCH(TablaPlatillos[[#This Row],[Insumo 11]],TablaInsumos[Nombre],0)),"") | AL15: =IFERROR(INDEX(TablaInsumos[Unidad de Compra],MATCH(TablaPlatillos[[#This Row],[Insumo 12]],TablaInsumos[Nombre],0)),"") | AN15: =25000/30 -> 833.33333 | AO15: =(3000+1000)/30 -> 133.33333 | AP15: =7000/30 -> 233.33333 | AQ15: 0 | AR15: =$J$26/30 -> 1055.5556 | AS15: 0
A16: 4 | B16: CopCake vainilla - Mantequilla | C16: 4500 | D16: Harina | E16: =IFERROR(INDEX(TablaInsumos[Unidad de Compra],MATCH(TablaPlatillos[[#This Row],[Insumo 1]],TablaInsumos[Nombre],0)),"") -> Gramo | F16: =500/30 -> 16.666667 | G16: Azúcar | H16: =IFERROR(INDEX(TablaInsumos[Unidad de Compra],MATCH(TablaPlatillos[[#This Row],[Insumo 2]],TablaInsumos[Nombre],0)),"") -> Gramo | I16: =400/30 -> 13.333333 | J16: Mantequilla | K16: =IFERROR(INDEX(TablaInsumos[Unidad de Compra],MATCH(TablaPlatillos[[#This Row],[Insumo 3]],TablaInsumos[Nombre],0)),"") -> Gramo | L16: =400/30 -> 13.333333 | M16: Huevos | N16: =IFERROR(INDEX(TablaInsumos[Unidad de Compra],MATCH(TablaPlatillos[[#This Row],[Insumo 4]],TablaInsumos[Nombre],0)),"") -> Unidad | O16: =8/30 -> 0.26666667 | P16: Leche entera | Q16: =IFERROR(INDEX(TablaInsumos[Unidad de Compra],MATCH(TablaPlatillos[[#This Row],[Insumo 5]],TablaInsumos[Nombre],0)),"") -> Mililitro | R16: =250/30 -> 8.3333333 | S16: Polvo para hornear | T16: =IFERROR(INDEX(TablaInsumos[Unidad de Compra],MATCH(TablaPlatillos[[#This Row],[Insumo 6]],TablaInsumos[Nombre],0)),"") -> Gramo | U16: =15/30 -> 0.5 | V16: Esencia de vainilla | W16: =IFERROR(INDEX(TablaInsumos[Unidad de Compra],MATCH(TablaPlatillos[[#This Row],[Insumo 7]],TablaInsumos[Nombre],0)),"") -> Mililitro | X16: =15/30 -> 0.5 | Y16: Sal (pizca) | Z16: =IFERROR(INDEX(TablaInsumos[Unidad de Compra],MATCH(TablaPlatillos[[#This Row],[Insumo 8]],TablaInsumos[Nombre],0)),"") -> Unidad | AA16: =1/30 -> 0.033333333 | AB16: Capacillo | AC16: =IFERROR(INDEX(TablaInsumos[Unidad de Compra],MATCH(TablaPlatillos[[#This Row],[Insumo 9]],TablaInsumos[Nombre],0)),"") -> Unidad | AD16: 1 | AE16: Caja x12 cupcakes | AF16: =IFERROR(INDEX(TablaInsumos[Unidad de Compra],MATCH(TablaPlatillos[[#This Row],[Insumo 10]],TablaInsumos[Nombre],0)),"") -> Unidad | AG16: =3/30 -> 0.1 | AI16: =IFERROR(INDEX(TablaInsumos[Unidad de Compra],MATCH(TablaPlatillos[[#This Row],[Insumo 11]],TablaInsumos[Nombre],0)),"") | AL16: =IFERROR(INDEX(TablaInsumos[Unidad de Compra],MATCH(TablaPlatillos[[#This Row],[Insumo 12]],TablaInsumos[Nombre],0)),"") | AN16: =25000/30 -> 833.33333 | AO16: =(3000+1000)/30 -> 133.33333 | AP16: =7000/30 -> 233.33333 | AQ16: 0 | AR16: =$J$26/30 -> 1055.5556 | AS16: 0
A17: 5 | B17: CopCake vainilla decorado - Vitina | C17: 6500 | D17: Harina | E17: =IFERROR(INDEX(TablaInsumos[Unidad de Compra],MATCH(TablaPlatillos[[#This Row],[Insumo 1]],TablaInsumos[Nombre],0)),"") -> Gramo | F17: =500/30 -> 16.666667 | G17: Azúcar | H17: =IFERROR(INDEX(TablaInsumos[Unidad de Compra],MATCH(TablaPlatillos[[#This Row],[Insumo 2]],TablaInsumos[Nombre],0)),"") -> Gramo | I17: =400/30 -> 13.333333 | J17: Vitina (margarina) | K17: =IFERROR(INDEX(TablaInsumos[Unidad de Compra],MATCH(TablaPlatillos[[#This Row],[Insumo 3]],TablaInsumos[Nombre],0)),"") -> Gramo | L17: =400/30 -> 13.333333 | M17: Huevos | N17: =IFERROR(INDEX(TablaInsumos[Unidad de Compra],MATCH(TablaPlatillos[[#This Row],[Insumo 4]],TablaInsumos[Nombre],0)),"") -> Unidad | O17: =8/30 -> 0.26666667 | P17: Leche entera | Q17: =IFERROR(INDEX(TablaInsumos[Unidad de Compra],MATCH(TablaPlatillos[[#This Row],[Insumo 5]],TablaInsumos[Nombre],0)),"") -> Mililitro | R17: =(250+20)/30 -> 9 | S17: Polvo para hornear | T17: =IFERROR(INDEX(TablaInsumos[Unidad de Compra],MATCH(TablaPlatillos[[#This Row],[Insumo 6]],TablaInsumos[Nombre],0)),"") -> Gramo | U17: =15/30 -> 0.5 | V17: Esencia de vainilla | W17: =IFERROR(INDEX(TablaInsumos[Unidad de Compra],MATCH(TablaPlatillos[[#This Row],[Insumo 7]],TablaInsumos[Nombre],0)),"") -> Mililitro | X17: =(15+5)/30 -> 0.66666667 | Y17: Sal (pizca) | Z17: =IFERROR(INDEX(TablaInsumos[Unidad de Compra],MATCH(TablaPlatillos[[#This Row],[Insumo 8]],TablaInsumos[Nombre],0)),"") -> Unidad | AA17: =1/30 -> 0.033333333 | AB17: Capacillo | AC17: =IFERROR(INDEX(TablaInsumos[Unidad de Compra],MATCH(TablaPlatillos[[#This Row],[Insumo 9]],TablaInsumos[Nombre],0)),"") -> Unidad | AD17: 1 | AE17: Caja x12 cupcakes | AF17: =IFERROR(INDEX(TablaInsumos[Unidad de Compra],MATCH(TablaPlatillos[[#This Row],[Insumo 10]],TablaInsumos[Nombre],0)),"") -> Unidad | AG17: =3/30 -> 0.1 | AH17: Mantequilla | AI17: =IFERROR(INDEX(TablaInsumos[Unidad de Compra],MATCH(TablaPlatillos[[#This Row],[Insumo 11]],TablaInsumos[Nombre],0)),"") -> Gramo | AJ17: =250/30 -> 8.3333333 | AK17: Azúcar glas | AL17: =IFERROR(INDEX(TablaInsumos[Unidad de Compra],MATCH(TablaPlatillos[[#This Row],[Insumo 12]],TablaInsumos[Nombre],0)),"") -> Gramo | AM17: =500/30 -> 16.666667 | AN17: =(25000+10000)/30 -> 1166.6667 | AO17: =(3000+1000)/30 -> 133.33333 | AP17: =7000/30 -> 233.33333 | AQ17: 0 | AR17: =$J$26/30 -> 1055.5556 | AS17: =500/30 -> 16.666667
A18: 6 | B18: CopCake vainilla decorado - Mantequilla | C18: 6500 | D18: Harina | E18: =IFERROR(INDEX(TablaInsumos[Unidad de Compra],MATCH(TablaPlatillos[[#This Row],[Insumo 1]],TablaInsumos[Nombre],0)),"") -> Gramo | F18: =500/30 -> 16.666667 | G18: Azúcar | H18: =IFERROR(INDEX(TablaInsumos[Unidad de Compra],MATCH(TablaPlatillos[[#This Row],[Insumo 2]],TablaInsumos[Nombre],0)),"") -> Gramo | I18: =400/30 -> 13.333333 | J18: Mantequilla | K18: =IFERROR(INDEX(TablaInsumos[Unidad de Compra],MATCH(TablaPlatillos[[#This Row],[Insumo 3]],TablaInsumos[Nombre],0)),"") -> Gramo | L18: =(400+250)/30 -> 21.666667 | M18: Huevos | N18: =IFERROR(INDEX(TablaInsumos[Unidad de Compra],MATCH(TablaPlatillos[[#This Row],[Insumo 4]],TablaInsumos[Nombre],0)),"") -> Unidad | O18: =8/30 -> 0.26666667 | P18: Leche entera | Q18: =IFERROR(INDEX(TablaInsumos[Unidad de Compra],MATCH(TablaPlatillos[[#This Row],[Insumo 5]],TablaInsumos[Nombre],0)),"") -> Mililitro | R18: =(250+20)/30 -> 9 | S18: Polvo para hornear | T18: =IFERROR(INDEX(TablaInsumos[Unidad de Compra],MATCH(TablaPlatillos[[#This Row],[Insumo 6]],TablaInsumos[Nombre],0)),"") -> Gramo | U18: =15/30 -> 0.5 | V18: Esencia de vainilla | W18: =IFERROR(INDEX(TablaInsumos[Unidad de Compra],MATCH(TablaPlatillos[[#This Row],[Insumo 7]],TablaInsumos[Nombre],0)),"") -> Mililitro | X18: =(15+5)/30 -> 0.66666667 | Y18: Sal (pizca) | Z18: =IFERROR(INDEX(TablaInsumos[Unidad de Compra],MATCH(TablaPlatillos[[#This Row],[Insumo 8]],TablaInsumos[Nombre],0)),"") -> Unidad | AA18: =1/30 -> 0.033333333 | AB18: Capacillo | AC18: =IFERROR(INDEX(TablaInsumos[Unidad de Compra],MATCH(TablaPlatillos[[#This Row],[Insumo 9]],TablaInsumos[Nombre],0)),"") -> Unidad | AD18: 1 | AE18: Caja x12 cupcakes | AF18: =IFERROR(INDEX(TablaInsumos[Unidad de Compra],MATCH(TablaPlatillos[[#This Row],[Insumo 10]],TablaInsumos[Nombre],0)),"") -> Unidad | AG18: =3/30 -> 0.1 | AH18: Azúcar glas | AI18: =IFERROR(INDEX(TablaInsumos[Unidad de Compra],MATCH(TablaPlatillos[[#This Row],[Insumo 11]],TablaInsumos[Nombre],0)),"") -> Gramo | AJ18: =500/30 -> 16.666667 | AL18: =IFERROR(INDEX(TablaInsumos[Unidad de Compra],MATCH(TablaPlatillos[[#This Row],[Insumo 12]],TablaInsumos[Nombre],0)),"") | AN18: =(25000+10000)/30 -> 1166.6667 | AO18: =(3000+1000)/30 -> 133.33333 | AP18: =7000/30 -> 233.33333 | AQ18: 0 | AR18: =$J$26/30 -> 1055.5556 | AS18: =500/30 -> 16.666667
A19: 7 | B19: CopCake de chocolate | C19: 5000 | D19: Harina | E19: =IFERROR(INDEX(TablaInsumos[Unidad de Compra],MATCH(TablaPlatillos[[#This Row],[Insumo 1]],TablaInsumos[Nombre],0)),"") -> Gramo | F19: =500/30 -> 16.666667 | G19: Azúcar | H19: =IFERROR(INDEX(TablaInsumos[Unidad de Compra],MATCH(TablaPlatillos[[#This Row],[Insumo 2]],TablaInsumos[Nombre],0)),"") -> Gramo | I19: =400/30 -> 13.333333 | J19: Vitina (margarina) | K19: =IFERROR(INDEX(TablaInsumos[Unidad de Compra],MATCH(TablaPlatillos[[#This Row],[Insumo 3]],TablaInsumos[Nombre],0)),"") -> Gramo | L19: =400/30 -> 13.333333 | M19: Huevos | N19: =IFERROR(INDEX(TablaInsumos[Unidad de Compra],MATCH(TablaPlatillos[[#This Row],[Insumo 4]],TablaInsumos[Nombre],0)),"") -> Unidad | O19: =8/30 -> 0.26666667 | P19: Leche entera | Q19: =IFERROR(INDEX(TablaInsumos[Unidad de Compra],MATCH(TablaPlatillos[[#This Row],[Insumo 5]],TablaInsumos[Nombre],0)),"") -> Mililitro | R19: =250/30 -> 8.3333333 | S19: Polvo para hornear | T19: =IFERROR(INDEX(TablaInsumos[Unidad de Compra],MATCH(TablaPlatillos[[#This Row],[Insumo 6]],TablaInsumos[Nombre],0)),"") -> Gramo | U19: =15/30 -> 0.5 | V19: Esencia de vainilla | W19: =IFERROR(INDEX(TablaInsumos[Unidad de Compra],MATCH(TablaPlatillos[[#This Row],[Insumo 7]],TablaInsumos[Nombre],0)),"") -> Mililitro | X19: =15/30 -> 0.5 | Y19: Sal (pizca) | Z19: =IFERROR(INDEX(TablaInsumos[Unidad de Compra],MATCH(TablaPlatillos[[#This Row],[Insumo 8]],TablaInsumos[Nombre],0)),"") -> Unidad | AA19: =1/30 -> 0.033333333 | AB19: Capacillo | AC19: =IFERROR(INDEX(TablaInsumos[Unidad de Compra],MATCH(TablaPlatillos[[#This Row],[Insumo 9]],TablaInsumos[Nombre],0)),"") -> Unidad | AD19: 1 | AE19: Caja x12 cupcakes | AF19: =IFERROR(INDEX(TablaInsumos[Unidad de Compra],MATCH(TablaPlatillos[[#This Row],[Insumo 10]],TablaInsumos[Nombre],0)),"") -> Unidad | AG19: =3/30 -> 0.1 | AI19: =IFERROR(INDEX(TablaInsumos[Unidad de Compra],MATCH(TablaPlatillos[[#This Row],[Insumo 11]],TablaInsumos[Nombre],0)),"") | AL19: =IFERROR(INDEX(TablaInsumos[Unidad de Compra],MATCH(TablaPlatillos[[#This Row],[Insumo 12]],TablaInsumos[Nombre],0)),"") | AN19: =25000/30 -> 833.33333 | AO19: =(3000+1000)/30 -> 133.33333 | AP19: =7000/30 -> 233.33333 | AQ19: 0 | AR19: =$J$26/30 -> 1055.5556 | AS19: 0
A20: 8 | E20: =IFERROR(INDEX(TablaInsumos[Unidad de Compra],MATCH(TablaPlatillos[[#This Row],[Insumo 1]],TablaInsumos[Nombre],0)),"") | H20: =IFERROR(INDEX(TablaInsumos[Unidad de Compra],MATCH(TablaPlatillos[[#This Row],[Insumo 2]],TablaInsumos[Nombre],0)),"") | K20: =IFERROR(INDEX(TablaInsumos[Unidad de Compra],MATCH(TablaPlatillos[[#This Row],[Insumo 3]],TablaInsumos[Nombre],0)),"") | N20: =IFERROR(INDEX(TablaInsumos[Unidad de Compra],MATCH(TablaPlatillos[[#This Row],[Insumo 4]],TablaInsumos[Nombre],0)),"") | Q20: =IFERROR(INDEX(TablaInsumos[Unidad de Compra],MATCH(TablaPlatillos[[#This Row],[Insumo 5]],TablaInsumos[Nombre],0)),"") | T20: =IFERROR(INDEX(TablaInsumos[Unidad de Compra],MATCH(TablaPlatillos[[#This Row],[Insumo 6]],TablaInsumos[Nombre],0)),"") | W20: =IFERROR(INDEX(TablaInsumos[Unidad de Compra],MATCH(TablaPlatillos[[#This Row],[Insumo 7]],TablaInsumos[Nombre],0)),"") | Z20: =IFERROR(INDEX(TablaInsumos[Unidad de Compra],MATCH(TablaPlatillos[[#This Row],[Insumo 8]],TablaInsumos[Nombre],0)),"") | AC20: =IFERROR(INDEX(TablaInsumos[Unidad de Compra],MATCH(TablaPlatillos[[#This Row],[Insumo 9]],TablaInsumos[Nombre],0)),"") | AF20: =IFERROR(INDEX(TablaInsumos[Unidad de Compra],MATCH(TablaPlatillos[[#This Row],[Insumo 10]],TablaInsumos[Nombre],0)),"") | AI20: =IFERROR(INDEX(TablaInsumos[Unidad de Compra],MATCH(TablaPlatillos[[#This Row],[Insumo 11]],TablaInsumos[Nombre],0)),"") | AL20: =IFERROR(INDEX(TablaInsumos[Unidad de Compra],MATCH(TablaPlatillos[[#This Row],[Insumo 12]],TablaInsumos[Nombre],0)),"")
A21: 9 | E21: =IFERROR(INDEX(TablaInsumos[Unidad de Compra],MATCH(TablaPlatillos[[#This Row],[Insumo 1]],TablaInsumos[Nombre],0)),"") | H21: =IFERROR(INDEX(TablaInsumos[Unidad de Compra],MATCH(TablaPlatillos[[#This Row],[Insumo 2]],TablaInsumos[Nombre],0)),"") | K21: =IFERROR(INDEX(TablaInsumos[Unidad de Compra],MATCH(TablaPlatillos[[#This Row],[Insumo 3]],TablaInsumos[Nombre],0)),"") | N21: =IFERROR(INDEX(TablaInsumos[Unidad de Compra],MATCH(TablaPlatillos[[#This Row],[Insumo 4]],TablaInsumos[Nombre],0)),"") | Q21: =IFERROR(INDEX(TablaInsumos[Unidad de Compra],MATCH(TablaPlatillos[[#This Row],[Insumo 5]],TablaInsumos[Nombre],0)),"") | T21: =IFERROR(INDEX(TablaInsumos[Unidad de Compra],MATCH(TablaPlatillos[[#This Row],[Insumo 6]],TablaInsumos[Nombre],0)),"") | W21: =IFERROR(INDEX(TablaInsumos[Unidad de Compra],MATCH(TablaPlatillos[[#This Row],[Insumo 7]],TablaInsumos[Nombre],0)),"") | Z21: =IFERROR(INDEX(TablaInsumos[Unidad de Compra],MATCH(TablaPlatillos[[#This Row],[Insumo 8]],TablaInsumos[Nombre],0)),"") | AC21: =IFERROR(INDEX(TablaInsumos[Unidad de Compra],MATCH(TablaPlatillos[[#This Row],[Insumo 9]],TablaInsumos[Nombre],0)),"") | AF21: =IFERROR(INDEX(TablaInsumos[Unidad de Compra],MATCH(TablaPlatillos[[#This Row],[Insumo 10]],TablaInsumos[Nombre],0)),"") | AI21: =IFERROR(INDEX(TablaInsumos[Unidad de Compra],MATCH(TablaPlatillos[[#This Row],[Insumo 11]],TablaInsumos[Nombre],0)),"") | AL21: =IFERROR(INDEX(TablaInsumos[Unidad de Compra],MATCH(TablaPlatillos[[#This Row],[Insumo 12]],TablaInsumos[Nombre],0)),"")
A22: 10 | E22: =IFERROR(INDEX(TablaInsumos[Unidad de Compra],MATCH(TablaPlatillos[[#This Row],[Insumo 1]],TablaInsumos[Nombre],0)),"") | H22: =IFERROR(INDEX(TablaInsumos[Unidad de Compra],MATCH(TablaPlatillos[[#This Row],[Insumo 2]],TablaInsumos[Nombre],0)),"") | K22: =IFERROR(INDEX(TablaInsumos[Unidad de Compra],MATCH(TablaPlatillos[[#This Row],[Insumo 3]],TablaInsumos[Nombre],0)),"") | N22: =IFERROR(INDEX(TablaInsumos[Unidad de Compra],MATCH(TablaPlatillos[[#This Row],[Insumo 4]],TablaInsumos[Nombre],0)),"") | Q22: =IFERROR(INDEX(TablaInsumos[Unidad de Compra],MATCH(TablaPlatillos[[#This Row],[Insumo 5]],TablaInsumos[Nombre],0)),"") | T22: =IFERROR(INDEX(TablaInsumos[Unidad de Compra],MATCH(TablaPlatillos[[#This Row],[Insumo 6]],TablaInsumos[Nombre],0)),"") | W22: =IFERROR(INDEX(TablaInsumos[Unidad de Compra],MATCH(TablaPlatillos[[#This Row],[Insumo 7]],TablaInsumos[Nombre],0)),"") | Z22: =IFERROR(INDEX(TablaInsumos[Unidad de Compra],MATCH(TablaPlatillos[[#This Row],[Insumo 8]],TablaInsumos[Nombre],0)),"") | AC22: =IFERROR(INDEX(TablaInsumos[Unidad de Compra],MATCH(TablaPlatillos[[#This Row],[Insumo 9]],TablaInsumos[Nombre],0)),"") | AF22: =IFERROR(INDEX(TablaInsumos[Unidad de Compra],MATCH(TablaPlatillos[[#This Row],[Insumo 10]],TablaInsumos[Nombre],0)),"") | AI22: =IFERROR(INDEX(TablaInsumos[Unidad de Compra],MATCH(TablaPlatillos[[#This Row],[Insumo 11]],TablaInsumos[Nombre],0)),"") | AL22: =IFERROR(INDEX(TablaInsumos[Unidad de Compra],MATCH(TablaPlatillos[[#This Row],[Insumo 12]],TablaInsumos[Nombre],0)),"")
B24: COSTOS POR TORTA (Deligaby, solo referencia) | C24: Mínimo | D24: Máximo | F24: MANTENIMIENTO DE EQUIPOS | I24: REPARTO
B25: Materia prima | C25: 40000 | D25: 50000 | F25: Horno | G25: 70000 | I25: Producciones que cubre | J25: 3
B26: Gastos oper. / domicilio | C26: 5000 | D26: 7000 | F26: Batidora | G26: 25000 | I26: Por torta / lote | J26: =IFERROR((G25+G26)/J25,0) -> 31666.667
B28: NOTAS Y SUPUESTOS
B29: 1. Corregido según los PDF "Costos y utilidad - Torta de vainilla" (28/09/2026) y "Costos y precio comercial - Cupcakes de vainilla" (29/09/2026). Torta: receta con 500 g de harina, se vende completa a $75.000, sin cobertura.
B30: 2. Todo está por UNIDAD (1 torta completa o 1 cupcake). Las cantidades del cupcake son el lote de 30 dividido entre 30 (ej.: 500/30 g de harina; 3 cajas x12 / 30).
B31: 3. Gastos por unidad (columnas Mano de Obra a Otros Gastos). Torta: mano de obra 1,5 h x $10.000; servicios luz $2.000 + agua/aseo $500; mantenimiento de equipos (horno + batidora, ver bloque MANTENIMIENTO DE EQUIPOS) por torta. Cupcake: mano de obra $25.000/30 (+$10.000/30 si es decorado); servicios ($3.000+$1.000)/30; mantenimiento por lote / 30; otros = manga $500/30 (decorado). Mano de obra y servicios son supuestos de los PDF.
B32: 4. Cambios sobre los PDF: se quitó la caja para torta ($4.481) y el desgaste estimado del PDF se reemplazó por el mantenimiento real del horno ($70.000) y la batidora ($25.000), repartido entre las producciones que indiques (celda J25). Un lote de 30 cupcakes cuenta como una producción.
B33: 5. Gastos directos (Mano de Obra, Servicios, Oper./Domicilio) se muestran en Explosión como total del LOTE y se dividen entre las unidades por lote (Postre C9: 30 cupcakes o 1 torta); por eso la Utilización de cada cupcake es 3,33% (1/30). Oper./Domicilio: $7.000 por lote de cupcakes ($7.000/30 por unidad); en tortas está en $0, escríbelo en la columna Oper. Domicilio si aplica. No incluye arriendo, impuestos, comisiones ni publicidad.
B34: 6. CopCake de chocolate: no hay PDF para este producto. Se dejó con la base del cupcake de vainilla (Vitina); falta agregar el cacao/chocolate y revisar su precio de $5.000.
B35: 7. Vitina: el precio usado es Vitina Hojaldre ($6.500 / 500 g). Si compras Vitina Professional (para ponqué), cambia el precio en Insumos. Elige el producto a analizar en la hoja Explosión (celda C10).

Sheet Explosión
C9: Seleccionar Platillo | O9: REFERENCIA: PRECIO PARA LOGRAR EL MARGEN DESEADO
C10: Torta Vainilla - Mantequilla
J12: Precio & Margen real | K12: =K13 -> 75000 | L12: =IFERROR(L42,"") -> 0 | O12: Precio necesario & Margen deseado | P12: =P13 -> 107142.86 | Q12: =Postre!$C$10 -> 0.3
C13: INSUMOS & LOGÍSTICA | J13: (+) Precio | K13: =IFERROR(INDEX(TablaPlatillos[Precio Platillo],MATCH($C$10,TablaPlatillos[Nombre de Platillo],0)),"") -> 75000 | L13: =IF(C10="","",100%) -> 1 | O13: (+) Precio necesario | P13: =IFERROR((P15+P31+P38)/(1-Q12),"") -> 107142.86 | Q13: =IF(P13="","",1) -> 1
J14: ="INGREDIENTES"&CHAR(10)&"$"&FIXED(K15,0) -> INGREDIENTES $40.837
C15: Producto | D15: Costo Unitario | E15: Cantidad | F15: Unidad | G15: Costo Total | H15: Ponderación | J15: (-) Costos | K15: =SUM(K16:K27) -> 40837.016 | L15: =IFERROR(K15/K13,"") -> 0.54449355 | O15: (-) Costos | P15: =SUM(P16:P27) -> 40837.016 | Q15: =IFERROR(P15/P$13,"") -> 0.38114548
C16: =IFERROR(INDEX(TablaPlatillos[Insumo 1],MATCH($C$10,TablaPlatillos[Nombre de Platillo],0))&"","") -> Harina | D16: =IF(C16="","",IFERROR(INDEX(TablaInsumos[Costo Unitario Total],MATCH(C16,TablaInsumos[Nombre],0)),"")) -> 4.5 | E16: =IF(C16="","",IFERROR(INDEX(TablaPlatillos[Cantidad 1],MATCH($C$10,TablaPlatillos[Nombre de Platillo],0)),"")) -> 500 | F16: =IF(C16="","",IFERROR(INDEX(TablaPlatillos[Unidad 1],MATCH($C$10,TablaPlatillos[Nombre de Platillo],0)),"")) -> Gramo | G16: =IFERROR(D16*E16,"") -> 2250 | H16: =IFERROR(G16/$G$28,"") -> 0.055097072 | J16: =IF(C16="","","(-) "&C16) -> (-) Harina | K16: =IF(G16="","",G16) -> 2250 | L16: =IFERROR(K16/$K$13,"") -> 0.03 | O16: =J16&"" -> (-) Harina | P16: =IF(G16="","",G16) -> 2250 | Q16: =IFERROR(P16/P$13,"") -> 0.021
C17: =IFERROR(INDEX(TablaPlatillos[Insumo 2],MATCH($C$10,TablaPlatillos[Nombre de Platillo],0))&"","") -> Azúcar | D17: =IF(C17="","",IFERROR(INDEX(TablaInsumos[Costo Unitario Total],MATCH(C17,TablaInsumos[Nombre],0)),"")) -> 5.1 | E17: =IF(C17="","",IFERROR(INDEX(TablaPlatillos[Cantidad 2],MATCH($C$10,TablaPlatillos[Nombre de Platillo],0)),"")) -> 400 | F17: =IF(C17="","",IFERROR(INDEX(TablaPlatillos[Unidad 2],MATCH($C$10,TablaPlatillos[Nombre de Platillo],0)),"")) -> Gramo | G17: =IFERROR(D17*E17,"") -> 2040 | H17: =IFERROR(G17/$G$28,"") -> 0.049954678 | J17: =IF(C17="","","(-) "&C17) -> (-) Azúcar | K17: =IF(G17="","",G17) -> 2040 | L17: =IFERROR(K17/$K$13,"") -> 0.0272 | O17: =J17&"" -> (-) Azúcar | P17: =IF(G17="","",G17) -> 2040 | Q17: =IFERROR(P17/P$13,"") -> 0.01904
C18: =IFERROR(INDEX(TablaPlatillos[Insumo 3],MATCH($C$10,TablaPlatillos[Nombre de Platillo],0))&"","") -> Mantequilla | D18: =IF(C18="","",IFERROR(INDEX(TablaInsumos[Costo Unitario Total],MATCH(C18,TablaInsumos[Nombre],0)),"")) -> 62.2 | E18: =IF(C18="","",IFERROR(INDEX(TablaPlatillos[Cantidad 3],MATCH($C$10,TablaPlatillos[Nombre de Platillo],0)),"")) -> 400 | F18: =IF(C18="","",IFERROR(INDEX(TablaPlatillos[Unidad 3],MATCH($C$10,TablaPlatillos[Nombre de Platillo],0)),"")) -> Gramo | G18: =IFERROR(D18*E18,"") -> 24880 | H18: =IFERROR(G18/$G$28,"") -> 0.60925117 | J18: =IF(C18="","","(-) "&C18) -> (-) Mantequilla | K18: =IF(G18="","",G18) -> 24880 | L18: =IFERROR(K18/$K$13,"") -> 0.33173333 | O18: =J18&"" -> (-) Mantequilla | P18: =IF(G18="","",G18) -> 24880 | Q18: =IFERROR(P18/P$13,"") -> 0.23221333
C19: =IFERROR(INDEX(TablaPlatillos[Insumo 4],MATCH($C$10,TablaPlatillos[Nombre de Platillo],0))&"","") -> Huevos | D19: =IF(C19="","",IFERROR(INDEX(TablaInsumos[Costo Unitario Total],MATCH(C19,TablaInsumos[Nombre],0)),"")) -> 890 | E19: =IF(C19="","",IFERROR(INDEX(TablaPlatillos[Cantidad 4],MATCH($C$10,TablaPlatillos[Nombre de Platillo],0)),"")) -> 8 | F19: =IF(C19="","",IFERROR(INDEX(TablaPlatillos[Unidad 4],MATCH($C$10,TablaPlatillos[Nombre de Platillo],0)),"")) -> Unidad | G19: =IFERROR(D19*E19,"") -> 7120 | H19: =IFERROR(G19/$G$28,"") -> 0.17435162 | J19: =IF(C19="","","(-) "&C19) -> (-) Huevos | K19: =IF(G19="","",G19) -> 7120 | L19: =IFERROR(K19/$K$13,"") -> 0.094933333 | O19: =J19&"" -> (-) Huevos | P19: =IF(G19="","",G19) -> 7120 | Q19: =IFERROR(P19/P$13,"") -> 0.066453333
C20: =IFERROR(INDEX(TablaPlatillos[Insumo 5],MATCH($C$10,TablaPlatillos[Nombre de Platillo],0))&"","") -> Leche entera | D20: =IF(C20="","",IFERROR(INDEX(TablaInsumos[Costo Unitario Total],MATCH(C20,TablaInsumos[Nombre],0)),"")) -> 4.49 | E20: =IF(C20="","",IFERROR(INDEX(TablaPlatillos[Cantidad 5],MATCH($C$10,TablaPlatillos[Nombre de Platillo],0)),"")) -> 250 | F20: =IF(C20="","",IFERROR(INDEX(TablaPlatillos[Unidad 5],MATCH($C$10,TablaPlatillos[Nombre de Platillo],0)),"")) -> Mililitro | G20: =IFERROR(D20*E20,"") -> 1122.5 | H20: =IFERROR(G20/$G$28,"") -> 0.027487317 | J20: =IF(C20="","","(-) "&C20) -> (-) Leche entera | K20: =IF(G20="","",G20) -> 1122.5 | L20: =IFERROR(K20/$K$13,"") -> 0.014966667 | O20: =J20&"" -> (-) Leche entera | P20: =IF(G20="","",G20) -> 1122.5 | Q20: =IFERROR(P20/P$13,"") -> 0.010476667
C21: =IFERROR(INDEX(TablaPlatillos[Insumo 6],MATCH($C$10,TablaPlatillos[Nombre de Platillo],0))&"","") -> Polvo para hornear | D21: =IF(C21="","",IFERROR(INDEX(TablaInsumos[Costo Unitario Total],MATCH(C21,TablaInsumos[Nombre],0)),"")) -> 94 | E21: =IF(C21="","",IFERROR(INDEX(TablaPlatillos[Cantidad 6],MATCH($C$10,TablaPlatillos[Nombre de Platillo],0)),"")) -> 15 | F21: =IF(C21="","",IFERROR(INDEX(TablaPlatillos[Unidad 6],MATCH($C$10,TablaPlatillos[Nombre de Platillo],0)),"")) -> Gramo | G21: =IFERROR(D21*E21,"") -> 1410 | H21: =IFERROR(G21/$G$28,"") -> 0.034527498 | J21: =IF(C21="","","(-) "&C21) -> (-) Polvo para hornear | K21: =IF(G21="","",G21) -> 1410 | L21: =IFERROR(K21/$K$13,"") -> 0.0188 | O21: =J21&"" -> (-) Polvo para hornear | P21: =IF(G21="","",G21) -> 1410 | Q21: =IFERROR(P21/P$13,"") -> 0.01316
C22: =IFERROR(INDEX(TablaPlatillos[Insumo 7],MATCH($C$10,TablaPlatillos[Nombre de Platillo],0))&"","") -> Esencia de vainilla | D22: =IF(C22="","",IFERROR(INDEX(TablaInsumos[Costo Unitario Total],MATCH(C22,TablaInsumos[Nombre],0)),"")) -> 30.967742 | E22: =IF(C22="","",IFERROR(INDEX(TablaPlatillos[Cantidad 7],MATCH($C$10,TablaPlatillos[Nombre de Platillo],0)),"")) -> 15 | F22: =IF(C22="","",IFERROR(INDEX(TablaPlatillos[Unidad 7],MATCH($C$10,TablaPlatillos[Nombre de Platillo],0)),"")) -> Mililitro | G22: =IFERROR(D22*E22,"") -> 464.51613 | H22: =IFERROR(G22/$G$28,"") -> 0.011374879 | J22: =IF(C22="","","(-) "&C22) -> (-) Esencia de vainilla | K22: =IF(G22="","",G22) -> 464.51613 | L22: =IFERROR(K22/$K$13,"") -> 0.0061935484 | O22: =J22&"" -> (-) Esencia de vainilla | P22: =IF(G22="","",G22) -> 464.51613 | Q22: =IFERROR(P22/P$13,"") -> 0.0043354839
C23: =IFERROR(INDEX(TablaPlatillos[Insumo 8],MATCH($C$10,TablaPlatillos[Nombre de Platillo],0))&"","") -> Sal (pizca) | D23: =IF(C23="","",IFERROR(INDEX(TablaInsumos[Costo Unitario Total],MATCH(C23,TablaInsumos[Nombre],0)),"")) -> 50 | E23: =IF(C23="","",IFERROR(INDEX(TablaPlatillos[Cantidad 8],MATCH($C$10,TablaPlatillos[Nombre de Platillo],0)),"")) -> 1 | F23: =IF(C23="","",IFERROR(INDEX(TablaPlatillos[Unidad 8],MATCH($C$10,TablaPlatillos[Nombre de Platillo],0)),"")) -> Unidad | G23: =IFERROR(D23*E23,"") -> 50 | H23: =IFERROR(G23/$G$28,"") -> 0.0012243794 | J23: =IF(C23="","","(-) "&C23) -> (-) Sal (pizca) | K23: =IF(G23="","",G23) -> 50 | L23: =IFERROR(K23/$K$13,"") -> 0.00066666667 | O23: =J23&"" -> (-) Sal (pizca) | P23: =IF(G23="","",G23) -> 50 | Q23: =IFERROR(P23/P$13,"") -> 0.00046666667
C24: =IFERROR(INDEX(TablaPlatillos[Insumo 9],MATCH($C$10,TablaPlatillos[Nombre de Platillo],0))&"","") -> Base de cartón torta | D24: =IF(C24="","",IFERROR(INDEX(TablaInsumos[Costo Unitario Total],MATCH(C24,TablaInsumos[Nombre],0)),"")) -> 1500 | E24: =IF(C24="","",IFERROR(INDEX(TablaPlatillos[Cantidad 9],MATCH($C$10,TablaPlatillos[Nombre de Platillo],0)),"")) -> 1 | F24: =IF(C24="","",IFERROR(INDEX(TablaPlatillos[Unidad 9],MATCH($C$10,TablaPlatillos[Nombre de Platillo],0)),"")) -> Unidad | G24: =IFERROR(D24*E24,"") -> 1500 | H24: =IFERROR(G24/$G$28,"") -> 0.036731381 | J24: =IF(C24="","","(-) "&C24) -> (-) Base de cartón torta | K24: =IF(G24="","",G24) -> 1500 | L24: =IFERROR(K24/$K$13,"") -> 0.02 | O24: =J24&"" -> (-) Base de cartón torta | P24: =IF(G24="","",G24) -> 1500 | Q24: =IFERROR(P24/P$13,"") -> 0.014
C25: =IFERROR(INDEX(TablaPlatillos[Insumo 10],MATCH($C$10,TablaPlatillos[Nombre de Platillo],0))&"","") | D25: =IF(C25="","",IFERROR(INDEX(TablaInsumos[Costo Unitario Total],MATCH(C25,TablaInsumos[Nombre],0)),"")) | E25: =IF(C25="","",IFERROR(INDEX(TablaPlatillos[Cantidad 10],MATCH($C$10,TablaPlatillos[Nombre de Platillo],0)),"")) | F25: =IF(C25="","",IFERROR(INDEX(TablaPlatillos[Unidad 10],MATCH($C$10,TablaPlatillos[Nombre de Platillo],0)),"")) | G25: =IFERROR(D25*E25,"") | H25: =IFERROR(G25/$G$28,"") | J25: =IF(C25="","","(-) "&C25) | K25: =IF(G25="","",G25) | L25: =IFERROR(K25/$K$13,"") | O25: =J25&"" | P25: =IF(G25="","",G25) | Q25: =IFERROR(P25/P$13,"")
C26: =IFERROR(INDEX(TablaPlatillos[Insumo 11],MATCH($C$10,TablaPlatillos[Nombre de Platillo],0))&"","") | D26: =IF(C26="","",IFERROR(INDEX(TablaInsumos[Costo Unitario Total],MATCH(C26,TablaInsumos[Nombre],0)),"")) | E26: =IF(C26="","",IFERROR(INDEX(TablaPlatillos[Cantidad 11],MATCH($C$10,TablaPlatillos[Nombre de Platillo],0)),"")) | F26: =IF(C26="","",IFERROR(INDEX(TablaPlatillos[Unidad 11],MATCH($C$10,TablaPlatillos[Nombre de Platillo],0)),"")) | G26: =IFERROR(D26*E26,"") | H26: =IFERROR(G26/$G$28,"") | J26: =IF(C26="","","(-) "&C26) | K26: =IF(G26="","",G26) | L26: =IFERROR(K26/$K$13,"") | O26: =J26&"" | P26: =IF(G26="","",G26) | Q26: =IFERROR(P26/P$13,"")
C27: =IFERROR(INDEX(TablaPlatillos[Insumo 12],MATCH($C$10,TablaPlatillos[Nombre de Platillo],0))&"","") | D27: =IF(C27="","",IFERROR(INDEX(TablaInsumos[Costo Unitario Total],MATCH(C27,TablaInsumos[Nombre],0)),"")) | E27: =IF(C27="","",IFERROR(INDEX(TablaPlatillos[Cantidad 12],MATCH($C$10,TablaPlatillos[Nombre de Platillo],0)),"")) | F27: =IF(C27="","",IFERROR(INDEX(TablaPlatillos[Unidad 12],MATCH($C$10,TablaPlatillos[Nombre de Platillo],0)),"")) | G27: =IFERROR(D27*E27,"") | H27: =IFERROR(G27/$G$28,"") | J27: =IF(C27="","","(-) "&C27) | K27: =IF(G27="","",G27) | L27: =IFERROR(K27/$K$13,"") | O27: =J27&"" | P27: =IF(G27="","",G27) | Q27: =IFERROR(P27/P$13,"")
C28: TOTAL | G28: =SUM(G16:G27) -> 40837.016 | H28: =SUM(H16:H27) -> 1 | J28: (=) Margen Bruto | K28: =IFERROR(K13-K15,"") -> 34162.984 | L28: =IFERROR(K28/K13,"") -> 0.45550645 | O28: (=) Margen Bruto | P28: =IFERROR(P13-P15,"") -> 66305.841 | Q28: =IFERROR(P28/P$13,"") -> 0.61885452
C30: GASTOS DIRECTOS
C31: Descripción | D31: Total | E31: Utilización | F31: Unidad | G31: Costo Total | H31: Ponderación | J31: (-) Gastos Directos | K31: =SUM(K32:K34) -> 17500 | L31: =IFERROR(K31/K13,"") -> 0.23333333 | O31: (-) Gastos Directos | P31: =SUM(P32:P34) -> 17500 | Q31: =IFERROR(P31/P$13,"") -> 0.16333333
C32: =Postre!F8 -> Mano de Obra | D32: =Postre!G8 -> 15000 | E32: =IF($C$10="","",1/Postre!$C$9) -> 1 | F32: Tiempo | G32: =D32/Postre!$C$9 -> 15000 | H32: =IF(C10="","",IFERROR(G32/$G$35,"")) -> 0.85714286 | J32: ="(-) "&C32 -> (-) Mano de Obra | K32: =IF(G32="","",G32) -> 15000 | L32: =IFERROR(K32/$K$13,"") -> 0.2 | O32: =J32&"" -> (-) Mano de Obra | P32: =IF(G32="","",G32) -> 15000 | Q32: =IFERROR(P32/P$13,"") -> 0.14
C33: =Postre!F9 -> Servicios (Agua, Luz, Gas) | D33: =Postre!G9 -> 2500 | E33: =IF($C$10="","",1/Postre!$C$9) -> 1 | F33: Moneda | G33: =D33/Postre!$C$9 -> 2500 | H33: =IF(C10="","",IFERROR(G33/$G$35,"")) -> 0.14285714 | J33: ="(-) "&C33 -> (-) Servicios (Agua, Luz, Gas) | K33: =IF(G33="","",G33) -> 2500 | L33: =IFERROR(K33/$K$13,"") -> 0.033333333 | O33: =J33&"" -> (-) Servicios (Agua, Luz, Gas) | P33: =IF(G33="","",G33) -> 2500 | Q33: =IFERROR(P33/P$13,"") -> 0.023333333
C34: =Postre!F10 -> Gastos Oper. / Domicilio | D34: =Postre!G10 -> 0 | E34: =IF($C$10="","",1/Postre!$C$9) -> 1 | F34: Moneda | G34: =D34/Postre!$C$9 -> 0 | H34: =IF(C10="","",IFERROR(G34/$G$35,"")) -> 0 | J34: ="(-) "&C34 -> (-) Gastos Oper. / Domicilio | K34: =IF(G34="","",G34) -> 0 | L34: =IFERROR(K34/$K$13,"") -> 0 | O34: =J34&"" -> (-) Gastos Oper. / Domicilio | P34: =IF(G34="","",G34) -> 0 | Q34: =IFERROR(P34/P$13,"") -> 0
C35: TOTAL | G35: =SUM(G32:G34) -> 17500 | H35: =SUM(H32:H34) -> 1 | J35: (=) Margen de Contribución | K35: =IFERROR(K28-K31,"") -> 16662.984 | L35: =IFERROR(K35/K13,"") -> 0.22217312 | O35: (=) Margen de Contribución | P35: =IFERROR(P28-P31,"") -> 48805.841 | Q35: =IFERROR(P35/P$13,"") -> 0.45552118
C37: GASTOS INDIRECTOS
C38: Producto | D38: Total | E38: Utilización | F38: Unidad | G38: Costo Total | H38: Ponderación | J38: (-) Gastos Indirectos | K38: =SUM(K39:K41) -> 16662.984 | L38: =IFERROR(K38/K13,"") -> 0.22217312 | O38: (-) Gastos Indirectos | P38: =SUM(P39:P41) -> 16662.984 | Q38: =IFERROR(P38/P$13,"") -> 0.15552118
C39: =Postre!I8 -> Sueldos Admin. | D39: =Postre!J8 -> 0 | E39: =IF($C$10="","",1/Postre!$C$9) -> 1 | F39: Tiempo | G39: =D39/Postre!$C$9 -> 0 | H39: =IF(C10="","",IFERROR(G39/$G$42,"")) -> 0 | J39: ="(-) "&C39 -> (-) Sueldos Admin. | K39: =IF(G39="","",G39) -> 0 | L39: =IFERROR(K39/$K$13,"") -> 0 | O39: =J39&"" -> (-) Sueldos Admin. | P39: =IF(G39="","",G39) -> 0 | Q39: =IFERROR(P39/P$13,"") -> 0
C40: =Postre!I9 -> Depreciación / desgaste | D40: =Postre!$G$25+Postre!$G$26 -> 95000 | E40: =IF($C$10="","",IF(Postre!$C$9=1,0.17539983022071307,1/(Postre!$J$25*Postre!$C$9))) -> 0.17539983 | F40: Moneda | G40: =D40*E40 -> 16662.984 | H40: =IF(C10="","",IFERROR(G40/$G$42,"")) -> 1 | J40: ="(-) "&C40 -> (-) Depreciación / desgaste | K40: =IF(G40="","",G40) -> 16662.984 | L40: =IFERROR(K40/$K$13,"") -> 0.22217312 | O40: =J40&"" -> (-) Depreciación / desgaste | P40: =IF(G40="","",G40) -> 16662.984 | Q40: =IFERROR(P40/P$13,"") -> 0.15552118
C41: =Postre!I10 -> Otros Gastos | D41: =Postre!J10 -> 0 | E41: =IF($C$10="","",1/Postre!$C$9) -> 1 | F41: Moneda | G41: =D41/Postre!$C$9 -> 0 | H41: =IF(C10="","",IFERROR(G41/$G$42,"")) -> 0 | J41: ="(-) "&C41 -> (-) Otros Gastos | K41: =IF(G41="","",G41) -> 0 | L41: =IFERROR(K41/$K$13,"") -> 0 | O41: =J41&"" -> (-) Otros Gastos | P41: =IF(G41="","",G41) -> 0 | Q41: =IFERROR(P41/P$13,"") -> 0
C42: TOTAL | G42: =SUM(G39:G41) -> 16662.984 | H42: =SUM(H39:H41) -> 1 | J42: (=) Utilidad del Producto | K42: =IFERROR(K35-K38,"") -> 0 | L42: =IFERROR(K42/K13,"") -> 0 | O42: (=) Utilidad del Producto | P42: =IFERROR(P35-P38,"") -> 32142.857 | Q42: =IFERROR(P42/P$13,"") -> 0.3
J43: Diferencia vs. margen deseado (Postre C10) | K43: =IFERROR(K42-K13*Postre!$C$10,"") -> -22500 | L43: =IFERROR(L42-Postre!$C$10,"") -> -0.3 | O43: Aumento de precio necesario | P43: =IFERROR(P13-K13,"") -> 32142.857 | Q43: =IFERROR(P13/K13-1,"") -> 0.42857143
C44: Información Gráfica | J44: Última actualización de la información: | L44: =TODAY() -> 46306
G47: =C32 -> Mano de Obra | H47: =G32 -> 15000
G48: =C33 -> Servicios (Agua, Luz, Gas) | H48: =G33 -> 2500
G49: =C34 -> Gastos Oper. / Domicilio | H49: =G34 -> 0
G50: =C35 -> TOTAL | H50: =G35 -> 17500
